ajax_datatable/__init__.py
ajax_datatable/app_settings.py
ajax_datatable/apps.py
ajax_datatable/columns.py
ajax_datatable/exceptions.py
ajax_datatable/filters.py
ajax_datatable/utils.py
ajax_datatable/views.py
ajax_datatable/static/ajax_datatable/.DS_Store
ajax_datatable/static/ajax_datatable/css/style.css
ajax_datatable/static/ajax_datatable/images/details_close.png
ajax_datatable/static/ajax_datatable/images/details_open.png
ajax_datatable/static/ajax_datatable/js/.DS_Store
ajax_datatable/static/ajax_datatable/js/utils.js
ajax_datatable/templates/ajax_datatable/row_tools.html
ajax_datatable/templatetags/__init__.py
ajax_datatable/templatetags/ajax_datatable_tags.py
ajax_datatable/tests/__init__.py
ajax_datatable/tests/test_autofilter.py
ajax_datatable/tests/test_choices_filters.py
ajax_datatable/tests/test_columndefs.py
ajax_datatable/tests/test_datatables_qs.py
ajax_datatable/tests/test_date_filters.py
ajax_datatable/tests/test_filters.py
tests/__init__.py
tests/manage.py
tests/models.py
tests/test_settings.py
tests/user/__init__.py
tests/user/models.py
tests/user/migrations/0001_initial.py
tests/user/migrations/__init__.py
django_ajax_datatable-4.4.3.dist-info/LICENSE
django_ajax_datatable-4.4.3.dist-info/METADATA
django_ajax_datatable-4.4.3.dist-info/WHEEL
django_ajax_datatable-4.4.3.dist-info/top_level.txt
django_ajax_datatable-4.4.3.dist-info/RECORD
