Metadata-Version: 2.1
Name: django-ajax-datatable
Version: 4.4.3
Summary: Helper class to integrate Django with datatables
Home-page: http://github.com/morlandi/django-ajax-datatable
Author: Mario Orlandi
Author-email: morlandi@brainstorm.it
License: MIT
Platform: UNKNOWN
Classifier: Development Status :: 5 - Production/Stable
Classifier: Operating System :: OS Independent
Classifier: Programming Language :: Python
Classifier: Framework :: Django
Classifier: Framework :: Django :: 2.2
Classifier: Framework :: Django :: 3.0
Classifier: Intended Audience :: Developers
Classifier: License :: OSI Approved :: BSD License
Classifier: Natural Language :: English
Classifier: Programming Language :: Python :: 3.7
